{
  "code": "47",
  "name": "Lot-et-Garonne",
  "regionCode": "NAQ",
  "regionName": "Nouvelle-Aquitaine",
  "asOf": "2026-07-21T18:53:37.965Z",
  "source": "https://data.economie.gouv.fr/explore/dataset/prix-des-carburants-en-france-flux-instantane-v2/",
  "freshnessFilterDays": 14,
  "stationCount": 77,
  "fuels": {
    "gazole": {
      "count": 74,
      "mean": 2.096,
      "median": 2.089,
      "min": 1.99,
      "max": 2.243
    },
    "sp95": {
      "count": 35,
      "mean": 2.0441,
      "median": 2.035,
      "min": 1.96,
      "max": 2.2
    },
    "sp98": {
      "count": 48,
      "mean": 2.0885,
      "median": 2.069,
      "min": 1.98,
      "max": 2.3
    },
    "e10": {
      "count": 59,
      "mean": 2.0022,
      "median": 1.99,
      "min": 1.939,
      "max": 2.122
    },
    "e85": {
      "count": 25,
      "mean": 0.852,
      "median": 0.843,
      "min": 0.771,
      "max": 0.998
    },
    "gplc": {
      "count": 5,
      "mean": 1.1206,
      "median": 1.139,
      "min": 1.01,
      "max": 1.19
    }
  },
  "stations": [
    {
      "id": "47000010",
      "cp": "47000",
      "ville": "Agen",
      "adresse": "21 Rue J B Peres",
      "pop": "R",
      "lat": 4420600,
      "lng": 63600,
      "fuels": {
        "gazole": 2.039,
        "sp98": 2.069,
        "e10": 1.969,
        "e85": 0.909
      }
    },
    {
      "id": "47000009",
      "cp": "47000",
      "ville": "Agen",
      "adresse": "NETTO, 530 AVENUE LEON BLUM",
      "pop": "R",
      "lat": 4421100,
      "lng": 64700,
      "fuels": {
        "gazole": 2.049,
        "sp95": 1.995,
        "e10": 1.939
      }
    },
    {
      "id": "47000003",
      "cp": "47000",
      "ville": "Agen",
      "adresse": "ZAC AGEN SUD",
      "pop": "R",
      "lat": 4418100,
      "lng": 61800,
      "fuels": {
        "gazole": 2.089,
        "sp95": 2.049,
        "e10": 1.989
      }
    },
    {
      "id": "47190001",
      "cp": "47190",
      "ville": "Aiguillon",
      "adresse": "Rue Anatole France",
      "pop": "R",
      "lat": 4429654,
      "lng": 34412,
      "fuels": {
        "gazole": 2.099,
        "sp95": 2.065,
        "sp98": 2.109,
        "e10": 2.01,
        "e85": 0.809
      }
    },
    {
      "id": "47220003",
      "cp": "47220",
      "ville": "Astaffort",
      "adresse": "Lotissement la Tuine",
      "pop": "R",
      "lat": 4405900,
      "lng": 65300,
      "fuels": {
        "gazole": 2.108,
        "sp98": 2.106,
        "e10": 1.987
      }
    },
    {
      "id": "47470001",
      "cp": "47470",
      "ville": "Beauville",
      "adresse": "313 AVENUE SAINT ROCH PICADOU",
      "pop": "R",
      "lat": 4427423.84457,
      "lng": 88436.41441,
      "fuels": {
        "gazole": 2.13,
        "e10": 2.06
      }
    },
    {
      "id": "47300002",
      "cp": "47300",
      "ville": "Bias",
      "adresse": "224 Avenue de Bordeaux",
      "pop": "R",
      "lat": 4440400,
      "lng": 68800,
      "fuels": {
        "gazole": 2.133,
        "sp98": 2.106,
        "e10": 1.988,
        "e85": 0.839,
        "gplc": 1.01
      }
    },
    {
      "id": "47300001",
      "cp": "47300",
      "ville": "Bias",
      "adresse": "Route de Bordeaux",
      "pop": "R",
      "lat": 4440400,
      "lng": 66900,
      "fuels": {
        "gazole": 2.05,
        "sp95": 2.015,
        "sp98": 2.038,
        "e10": 1.982
      }
    },
    {
      "id": "47550009",
      "cp": "47550",
      "ville": "Boé",
      "adresse": "1500 Avenue du Docteur Jean Noguès",
      "pop": "R",
      "lat": 4418500,
      "lng": 66400,
      "fuels": {
        "gazole": 2.119,
        "sp98": 2.119,
        "e10": 1.999,
        "gplc": 1.139
      }
    },
    {
      "id": "47550012",
      "cp": "47550",
      "ville": "Boé",
      "adresse": "Av. de Lacapelette",
      "pop": "R",
      "lat": 4417846.75866,
      "lng": 63321.89421,
      "fuels": {
        "gazole": 2.089,
        "sp98": 2.065,
        "e10": 1.955
      }
    },
    {
      "id": "47550007",
      "cp": "47550",
      "ville": "Boé",
      "adresse": "RTE DE TOULOUSE RN 113",
      "pop": "R",
      "lat": 4418603,
      "lng": 66242,
      "fuels": {
        "e85": 0.869
      }
    },
    {
      "id": "47240002",
      "cp": "47240",
      "ville": "Bon-Encontre",
      "adresse": "Redon Lieu-dit Mon Repos - RN 113",
      "pop": "R",
      "lat": 4419000,
      "lng": 65564,
      "fuels": {
        "gazole": 2.049,
        "sp95": 2.049,
        "e10": 1.955
      }
    },
    {
      "id": "47310007",
      "cp": "47310",
      "ville": "Brax",
      "adresse": "190 Avenue des Landes",
      "pop": "R",
      "lat": 4420000,
      "lng": 55400,
      "fuels": {
        "gazole": 2.089,
        "sp95": 2.05,
        "sp98": 2.089,
        "e10": 2.02
      }
    },
    {
      "id": "47440001",
      "cp": "47440",
      "ville": "Casseneuil",
      "adresse": "LA RIGALE",
      "pop": "R",
      "lat": 4444100,
      "lng": 63100,
      "fuels": {
        "gazole": 1.99,
        "sp95": 1.99
      }
    },
    {
      "id": "47240001",
      "cp": "47240",
      "ville": "Castelculier",
      "adresse": "RD 813",
      "pop": "R",
      "lat": 4418100,
      "lng": 67300,
      "fuels": {
        "gazole": 2.049,
        "sp98": 2.065,
        "e10": 1.955,
        "e85": 0.899
      }
    },
    {
      "id": "47700002",
      "cp": "47700",
      "ville": "Casteljaloux",
      "adresse": "16 rue Pierre Dufiet",
      "pop": "R",
      "lat": 4431900,
      "lng": 9300,
      "fuels": {
        "gazole": 2.079,
        "sp98": 2.125,
        "e10": 1.989
      }
    },
    {
      "id": "47700001",
      "cp": "47700",
      "ville": "Casteljaloux",
      "adresse": "3 rue henri iv",
      "pop": "R",
      "lat": 4431400,
      "lng": 8100,
      "fuels": {
        "gazole": 2.099,
        "sp95": 2.019,
        "sp98": 2.047,
        "e10": 1.999,
        "e85": 0.899
      }
    },
    {
      "id": "47260001",
      "cp": "47260",
      "ville": "Castelmoron-sur-Lot",
      "adresse": "120 route de st Etienne de fougères",
      "pop": "R",
      "lat": 4440168.07204,
      "lng": 49923.26087,
      "fuels": {
        "gazole": 2.107,
        "sp98": 2.061,
        "e10": 1.975,
        "e85": 0.771
      }
    },
    {
      "id": "47330001",
      "cp": "47330",
      "ville": "Castillonnès",
      "adresse": "RN 21 - MONPLAISIR",
      "pop": "R",
      "lat": 4464300,
      "lng": 59400,
      "fuels": {
        "gazole": 2.089,
        "sp98": 2.128,
        "e10": 1.994
      }
    },
    {
      "id": "47320003",
      "cp": "47320",
      "ville": "Clairac",
      "adresse": "Quai Gambetta",
      "pop": "R",
      "lat": 4435700,
      "lng": 38200,
      "fuels": {
        "gazole": 2.139,
        "sp98": 2.129,
        "e10": 2.029
      }
    },
    {
      "id": "47450003",
      "cp": "47450",
      "ville": "Colayrac-Saint-Cirq",
      "adresse": "246 AVENUE DE LA LIBERATION",
      "pop": "R",
      "lat": 4422130.48989,
      "lng": 55686.48032,
      "fuels": {
        "gazole": 1.99,
        "sp95": 1.99,
        "e85": 0.827
      }
    },
    {
      "id": "47450002",
      "cp": "47450",
      "ville": "Colayrac-Saint-Cirq",
      "adresse": "70 route de bibes",
      "pop": "R",
      "lat": 4422087,
      "lng": 57989,
      "fuels": {
        "gazole": 2.089,
        "sp95": 2.049,
        "e10": 1.989
      }
    },
    {
      "id": "47160002",
      "cp": "47160",
      "ville": "Damazan",
      "adresse": "13 AVENUE DES LANDES",
      "pop": "R",
      "lat": 4428798,
      "lng": 27223.7,
      "fuels": {
        "gazole": 2.097,
        "sp98": 2.09,
        "e10": 2.01,
        "e85": 0.795
      }
    },
    {
      "id": "47120003",
      "cp": "47120",
      "ville": "Duras",
      "adresse": "83 CHEMIN BOUTERES POURRAOU",
      "pop": "R",
      "lat": 4467769.3,
      "lng": 19050.4,
      "fuels": {
        "gazole": 2.119,
        "sp95": 1.999,
        "sp98": 2.061
      }
    },
    {
      "id": "47120002",
      "cp": "47120",
      "ville": "Duras",
      "adresse": "rte Nationale 708",
      "pop": "R",
      "lat": 4466500,
      "lng": 19400,
      "fuels": {
        "gazole": 2.09,
        "e10": 2.03
      }
    },
    {
      "id": "47310003",
      "cp": "47310",
      "ville": "Estillac",
      "adresse": "45 Route d'Agen",
      "pop": "R",
      "lat": 4418400,
      "lng": 57600,
      "fuels": {
        "gazole": 2.1,
        "sp95": 1.96,
        "sp98": 1.98
      }
    },
    {
      "id": "47220002",
      "cp": "47220",
      "ville": "Fals",
      "adresse": "Lieu-dit La Garenne",
      "pop": "R",
      "lat": 4411451,
      "lng": 70472,
      "fuels": {
        "gazole": 2.06,
        "e10": 1.99
      }
    },
    {
      "id": "47510001",
      "cp": "47510",
      "ville": "Foulayronnes",
      "adresse": "21 Avenue du Caoulet",
      "pop": "R",
      "lat": 4423225,
      "lng": 63880,
      "fuels": {
        "gazole": 2.243,
        "sp95": 2.124
      }
    },
    {
      "id": "47510002",
      "cp": "47510",
      "ville": "Foulayronnes",
      "adresse": "Zone Le Rouge ZAC de Foulayronnes",
      "pop": "R",
      "lat": 4423600,
      "lng": 64300,
      "fuels": {
        "gazole": 2.119,
        "sp98": 2.039,
        "e10": 1.999
      }
    },
    {
      "id": "47500010",
      "cp": "47500",
      "ville": "Fumel",
      "adresse": "372 route de périgueux",
      "pop": "R",
      "lat": 4449338.41566,
      "lng": 94898.41184,
      "fuels": {
        "sp98": 1.999
      }
    },
    {
      "id": "47420001",
      "cp": "47420",
      "ville": "Houeillès",
      "adresse": "Rue Fernand Aude RD8",
      "pop": "R",
      "lat": 4419478.6,
      "lng": 3529.79,
      "fuels": {
        "gazole": 2.13,
        "e10": 2.06
      }
    },
    {
      "id": "47240003",
      "cp": "47240",
      "ville": "Lafox",
      "adresse": "94 ROUTE DE PUYMIROL",
      "pop": "R",
      "lat": 4416859.20334,
      "lng": 70122.27761,
      "fuels": {
        "gazole": 2.07,
        "sp95": 2.054,
        "sp98": 2.105,
        "e10": 1.989,
        "e85": 0.809
      }
    },
    {
      "id": "47310005",
      "cp": "47310",
      "ville": "Laplume",
      "adresse": "15 Route d'Agen",
      "pop": "R",
      "lat": 4411200,
      "lng": 52400,
      "fuels": {
        "gazole": 2.089,
        "sp98": 2.089,
        "e10": 1.989
      }
    },
    {
      "id": "47340001",
      "cp": "47340",
      "ville": "Laroque-Timbaut",
      "adresse": "1 rue BELJOUAN",
      "pop": "R",
      "lat": 4428600,
      "lng": 76000,
      "fuels": {
        "gazole": 2.053,
        "sp95": 1.999,
        "sp98": 2.032
      }
    },
    {
      "id": "47410000",
      "cp": "47410",
      "ville": "Lauzun",
      "adresse": "Lieu-dit Saint-Étienne",
      "pop": "R",
      "lat": 4462900,
      "lng": 45200,
      "fuels": {
        "gazole": 2.13,
        "e10": 2.06,
        "e85": 0.89
      }
    },
    {
      "id": "47230001",
      "cp": "47230",
      "ville": "Lavardac",
      "adresse": "D408 Route de Mézin",
      "pop": "R",
      "lat": 4417075.58581,
      "lng": 29310.98757,
      "fuels": {
        "gazole": 2.089,
        "sp95": 2.039,
        "sp98": 2.059,
        "e85": 0.815
      }
    },
    {
      "id": "47390003",
      "cp": "47390",
      "ville": "Layrac",
      "adresse": "lieu dit la tuilerie",
      "pop": "R",
      "lat": 4412443.84334,
      "lng": 65824.74509,
      "fuels": {
        "gazole": 2.15,
        "sp95": 2.135,
        "sp98": 2.3
      }
    },
    {
      "id": "47430002",
      "cp": "47430",
      "ville": "Le Mas-d'Agenais",
      "adresse": "AIRE DE MAS D'AGENAIS A62",
      "pop": "A",
      "lat": 4440495,
      "lng": 18765,
      "fuels": {
        "gazole": 2.176,
        "sp98": 2.175,
        "e10": 2.086,
        "e85": 0.94,
        "gplc": 1.074
      }
    },
    {
      "id": "47520004",
      "cp": "47520",
      "ville": "Le Passage",
      "adresse": "106 AVENUE DES PYRENEES",
      "pop": "R",
      "lat": 4417140.63,
      "lng": 60855.8,
      "fuels": {
        "gazole": 2.119,
        "e85": 0.829
      }
    },
    {
      "id": "47520003",
      "cp": "47520",
      "ville": "Le Passage",
      "adresse": "La Ville",
      "pop": "R",
      "lat": 4419000,
      "lng": 60500,
      "fuels": {
        "gazole": 2.089,
        "sp98": 2.089,
        "e10": 1.989
      }
    },
    {
      "id": "47200012",
      "cp": "47200",
      "ville": "Marmande",
      "adresse": "118 Avenue Jean Jaurès",
      "pop": "R",
      "lat": 4450800,
      "lng": 14700,
      "fuels": {
        "gazole": 2.069,
        "sp98": 2.05,
        "e10": 1.985
      }
    },
    {
      "id": "47200004",
      "cp": "47200",
      "ville": "Marmande",
      "adresse": "41 AVENUE GEORGES POMPIDOU",
      "pop": "R",
      "lat": 4450800,
      "lng": 19100,
      "fuels": {
        "gazole": 2.189,
        "sp98": 2.149,
        "e10": 2.049
      }
    },
    {
      "id": "47200013",
      "cp": "47200",
      "ville": "Marmande",
      "adresse": "6-8 RUE FRANCOIS MAURIAC",
      "pop": "R",
      "lat": 4450089.445,
      "lng": 16388.36182,
      "fuels": {
        "gazole": 2.099,
        "sp95": 2.045,
        "e10": 1.999
      }
    },
    {
      "id": "47200008",
      "cp": "47200",
      "ville": "Marmande",
      "adresse": "Avenue Hubert Ruffe",
      "pop": "R",
      "lat": 4448400,
      "lng": 18400,
      "fuels": {
        "gazole": 2.069,
        "sp95": 2.029,
        "sp98": 2.069
      }
    },
    {
      "id": "47200002",
      "cp": "47200",
      "ville": "Marmande",
      "adresse": "PONT DES SABLES",
      "pop": "R",
      "lat": 4446400,
      "lng": 14000,
      "fuels": {
        "e10": 1.99,
        "e85": 0.859
      }
    },
    {
      "id": "47200005",
      "cp": "47200",
      "ville": "Marmande",
      "adresse": "Route de Bordeaux",
      "pop": "R",
      "lat": 4451200,
      "lng": 13500,
      "fuels": {
        "gazole": 2.069,
        "sp95": 2.029,
        "sp98": 2.069,
        "e10": 1.985,
        "e85": 0.859,
        "gplc": 1.19
      }
    },
    {
      "id": "47800003",
      "cp": "47800",
      "ville": "Miramont-de-Guyenne",
      "adresse": "Avenue Alfred Court",
      "pop": "R",
      "lat": 4459548,
      "lng": 35238,
      "fuels": {
        "gazole": 2.088,
        "sp95": 2.035
      }
    },
    {
      "id": "47290003",
      "cp": "47290",
      "ville": "Monbahus",
      "adresse": "2 rue du champ de foire",
      "pop": "R",
      "lat": 4454899.75,
      "lng": 53641.03833,
      "fuels": {
        "gazole": 2.13,
        "e10": 2.06
      }
    },
    {
      "id": "47150003",
      "cp": "47150",
      "ville": "Monflanquin",
      "adresse": "D124 - Route de VILLENEUVE-sur-Lot - VIGNES DE LA JUSTICE",
      "pop": "R",
      "lat": 4452472.87874,
      "lng": 76066.09882,
      "fuels": {
        "gazole": 2.079,
        "sp98": 2.059,
        "e10": 1.988
      }
    },
    {
      "id": "47500003",
      "cp": "47500",
      "ville": "Montayral",
      "adresse": "ZA Les portes du Quercy",
      "pop": "R",
      "lat": 4448600,
      "lng": 97900,
      "fuels": {
        "gazole": 2.089,
        "sp95": 2.061,
        "sp98": 2.069
      }
    },
    {
      "id": "47600007",
      "cp": "47600",
      "ville": "Nérac",
      "adresse": "34 Avenue Georges Clemenceau",
      "pop": "R",
      "lat": 4413381.1,
      "lng": 34580.9,
      "fuels": {
        "gazole": 1.99,
        "e10": 1.99
      }
    },
    {
      "id": "47600006",
      "cp": "47600",
      "ville": "Nérac",
      "adresse": "Boulevard Maréchal Foch / 3 rue Durey",
      "pop": "R",
      "lat": 4414400,
      "lng": 33200,
      "fuels": {
        "gazole": 2.039,
        "sp98": 2.059,
        "e10": 1.999,
        "e85": 0.835
      }
    },
    {
      "id": "47600003",
      "cp": "47600",
      "ville": "Nérac",
      "adresse": "ZI LABARRE",
      "pop": "R",
      "lat": 4414837.79368,
      "lng": 32456.43531,
      "fuels": {
        "gazole": 2.049,
        "sp98": 2.047,
        "e10": 1.958
      }
    },
    {
      "id": "47480003",
      "cp": "47480",
      "ville": "Pont-du-Casse",
      "adresse": "974 AV DE CAHORS",
      "pop": "R",
      "lat": 4422600,
      "lng": 67200,
      "fuels": {
        "gazole": 2.219,
        "sp95": 2.124,
        "e85": 0.836
      }
    },
    {
      "id": "47480002",
      "cp": "47480",
      "ville": "Pont-du-Casse",
      "adresse": "LIEUDIT LE BOURG C.C.",
      "pop": "R",
      "lat": 4423000,
      "lng": 67700,
      "fuels": {
        "gazole": 2.089,
        "sp95": 2.049,
        "sp98": 2.099,
        "e10": 1.989
      }
    },
    {
      "id": "47130001",
      "cp": "47130",
      "ville": "Port-Sainte-Marie",
      "adresse": "2734 ROUTE DE BORDEAUX",
      "pop": "R",
      "lat": 4425200,
      "lng": 38200,
      "fuels": {
        "gazole": 2.135,
        "sp95": 2.08,
        "sp98": 2.138,
        "e10": 2.02,
        "e85": 0.809
      }
    },
    {
      "id": "47360001",
      "cp": "47360",
      "ville": "Prayssas",
      "adresse": "LE BOURG",
      "pop": "R",
      "lat": 4428700,
      "lng": 50900,
      "fuels": {
        "gazole": 2.13,
        "e10": 2.06
      }
    },
    {
      "id": "47300008",
      "cp": "47300",
      "ville": "Pujols",
      "adresse": "2, rue Bir-Hakeim",
      "pop": "R",
      "lat": 4439300,
      "lng": 69200,
      "fuels": {
        "gazole": 2.069,
        "sp98": 2.059,
        "e10": 1.979,
        "e85": 0.799
      }
    },
    {
      "id": "47310004",
      "cp": "47310",
      "ville": "Roquefort",
      "adresse": "Place du 8 Mai 1945",
      "pop": "R",
      "lat": 4417600,
      "lng": 56000,
      "fuels": {
        "gazole": 2.088,
        "sp98": 2.099,
        "e10": 1.998
      }
    },
    {
      "id": "47800002",
      "cp": "47800",
      "ville": "Saint-Pardoux-Isaac",
      "adresse": "Au Rébéquet",
      "pop": "R",
      "lat": 4461364,
      "lng": 36024,
      "fuels": {
        "gazole": 2.088,
        "sp95": 2.035,
        "e10": 1.979
      }
    },
    {
      "id": "47140002",
      "cp": "47140",
      "ville": "Saint-Sylvestre-sur-Lot",
      "adresse": "Avenue de la Myre Mory",
      "pop": "R",
      "lat": 4439673,
      "lng": 80632,
      "fuels": {
        "gazole": 2.099,
        "sp98": 2.069,
        "e10": 1.959
      }
    },
    {
      "id": "47500007",
      "cp": "47500",
      "ville": "Saint-Vite",
      "adresse": "180 ZONE DU BOSCLA",
      "pop": "R",
      "lat": 4447600,
      "lng": 95100,
      "fuels": {
        "gazole": 2.08,
        "sp95": 2.018,
        "sp98": 2.06,
        "e10": 1.964
      }
    },
    {
      "id": "47180002",
      "cp": "47180",
      "ville": "Sainte-Bazeille",
      "adresse": "lieu dit Beylard RD 813",
      "pop": "R",
      "lat": 4452737.53853,
      "lng": 10253.26072,
      "fuels": {
        "gazole": 2.055,
        "sp98": 2.049,
        "e10": 1.965,
        "e85": 0.859
      }
    },
    {
      "id": "47310006",
      "cp": "47310",
      "ville": "Sainte-Colombe-en-Bruilhois",
      "adresse": "AUTOROUTE A62 - AIRE AGEN PORTE D'AQUITAINE NORD",
      "pop": "A",
      "lat": 4419918.44185,
      "lng": 50903.93687,
      "fuels": {
        "gazole": 2.216,
        "sp98": 2.235,
        "e10": 2.122,
        "e85": 0.998
      }
    },
    {
      "id": "47140001",
      "cp": "47110",
      "ville": "Sainte-Livrade-sur-Lot",
      "adresse": "Route de Villeneuve",
      "pop": "R",
      "lat": 4440100,
      "lng": 61400,
      "fuels": {
        "gazole": 2.099,
        "sp98": 2.099,
        "e10": 1.999
      }
    },
    {
      "id": "47250001",
      "cp": "47250",
      "ville": "Samazan",
      "adresse": "lieu dit les Barths",
      "pop": "R",
      "lat": 4443100,
      "lng": 12900,
      "fuels": {
        "gazole": 1.99,
        "e10": 1.99,
        "e85": 0.859
      }
    },
    {
      "id": "47500008",
      "cp": "47500",
      "ville": "Sauveterre-la-Lémance",
      "adresse": "le bourg - 292 D710",
      "pop": "R",
      "lat": 4459267.57676,
      "lng": 101494.63248,
      "fuels": {
        "gazole": 2.13,
        "e10": 2.06
      }
    },
    {
      "id": "47400003",
      "cp": "47400",
      "ville": "Tonneins",
      "adresse": "Avenue Beauregard",
      "pop": "R",
      "lat": 4439700,
      "lng": 32500,
      "fuels": {
        "gazole": 2.09,
        "sp95": 1.999,
        "sp98": 2.079,
        "e10": 1.999
      }
    },
    {
      "id": "47400002",
      "cp": "47400",
      "ville": "Tonneins",
      "adresse": "Avenue Pierre Mendes France",
      "pop": "R",
      "lat": 4440000,
      "lng": 29900,
      "fuels": {
        "gazole": 2.138,
        "sp95": 2.091,
        "sp98": 2.131,
        "e10": 2.057,
        "e85": 0.843,
        "gplc": 1.19
      }
    },
    {
      "id": "47400004",
      "cp": "47400",
      "ville": "Tonneins",
      "adresse": "RUE MENDES FRANCE",
      "pop": "R",
      "lat": 4440100,
      "lng": 29900,
      "fuels": {
        "gazole": 2.109,
        "e10": 1.993,
        "e85": 0.845
      }
    },
    {
      "id": "47300004",
      "cp": "47300",
      "ville": "Villeneuve-sur-Lot",
      "adresse": "2093 Route Nationale 21 SOUBIROUS",
      "pop": "R",
      "lat": 4445800,
      "lng": 69500,
      "fuels": {
        "gazole": 2.178,
        "sp95": 2.118,
        "sp98": 2.159
      }
    },
    {
      "id": "47000001",
      "cp": "47300",
      "ville": "Villeneuve-sur-Lot",
      "adresse": "92 Avenue Henri BARBUSSE",
      "pop": "R",
      "lat": 4439800,
      "lng": 72900,
      "fuels": {
        "gazole": 2.21,
        "sp95": 2.2
      }
    },
    {
      "id": "47300006",
      "cp": "47300",
      "ville": "Villeneuve-sur-Lot",
      "adresse": "Route d'Agen",
      "pop": "R",
      "lat": 4439627.25078,
      "lng": 70675.26424,
      "fuels": {
        "gazole": 2.049,
        "sp95": 2.015,
        "sp98": 2.069,
        "e10": 1.979
      }
    },
    {
      "id": "47300003",
      "cp": "47300",
      "ville": "Villeneuve-sur-Lot",
      "adresse": "Route de Fumel",
      "pop": "R",
      "lat": 4440800,
      "lng": 73500,
      "fuels": {
        "gazole": 2.079,
        "sp95": 2.017,
        "sp98": 2.059,
        "e10": 1.988
      }
    },
    {
      "id": "47210002",
      "cp": "47210",
      "ville": "Villeréal",
      "adresse": "Au Caillou",
      "pop": "R",
      "lat": 4462400,
      "lng": 74100,
      "fuels": {
        "gazole": 2.13,
        "e10": 2.06
      }
    },
    {
      "id": "47210001",
      "cp": "47210",
      "ville": "Villeréal",
      "adresse": "Route de castillonnes",
      "pop": "R",
      "lat": 4463500,
      "lng": 73800,
      "fuels": {
        "gazole": 2.088,
        "sp95": 2.029,
        "e10": 1.98
      }
    },
    {
      "id": "47200011",
      "cp": "47200",
      "ville": "Virazeil",
      "adresse": "1440 rte de Miramont de Guyenne",
      "pop": "R",
      "lat": 4450500,
      "lng": 22100,
      "fuels": {
        "gazole": 1.99,
        "sp95": 1.99
      }
    }
  ]
}